completime/__init__.py
completime/time.py
completime-0.0.1.dist-info/METADATA
completime-0.0.1.dist-info/WHEEL
completime-0.0.1.dist-info/licenses/LICENSE
completime-0.0.1.dist-info/RECORD
