Metadata-Version: 2.4
Name: completime
Version: 0.0.1
Summary: Library for getting completion time.
Project-URL: Homepage, https://github.com/treizd/CompleTime/tree/master
Project-URL: Issues, https://github.com/treizd/CompleTime/issues
Author-email: treizd <sqeshexaero@gmail.com>
License-File: LICENSE
Classifier: License :: OSI Approved :: MIT License
Classifier: Operating System :: OS Independent
Classifier: Programming Language :: Python :: 3
Requires-Python: >=3.6.0
